peftee/__init__.py
peftee/data_collator.py
peftee/gds_loader.py
peftee/llama.py
peftee/trainer.py
peftee/utils.py
peftee-0.0.2.dist-info/licenses/LICENSE
peftee-0.0.2.dist-info/METADATA
peftee-0.0.2.dist-info/WHEEL
peftee-0.0.2.dist-info/top_level.txt
peftee-0.0.2.dist-info/RECORD
