Metadata-Version: 2.4
Name: peftee
Version: 0.0.2
Summary: LLM fine-tuning library
Author-email: Anuar Sharafudinov <anuarsh@ailabs.us>
License: MIT License
Project-URL: Homepage, https://github.com/Mega4alik/tlm
Project-URL: Bug Tracker, https://github.com/Mega4alik/tlm/issues
Requires-Python: >=3.10
License-File: LICENSE
Requires-Dist: numpy
Requires-Dist: torch>2.6.0
Requires-Dist: transformers>=4.57.0
Requires-Dist: peft
Dynamic: license-file
